pyramid_simpleform/__init__.py
pyramid_simpleform/renderers.py
pyramid_simpleform/tests.py
pyramid_simpleform-0.7.dev0.dist-info/DESCRIPTION.rst
pyramid_simpleform-0.7.dev0.dist-info/METADATA
pyramid_simpleform-0.7.dev0.dist-info/metadata.json
pyramid_simpleform-0.7.dev0.dist-info/RECORD
pyramid_simpleform-0.7.dev0.dist-info/top_level.txt
pyramid_simpleform-0.7.dev0.dist-info/WHEEL
